[
  {
    "stationuuid": "b0d62ef7-c695-11e8-a498-52543be04c81",
    "name": "Medinabaye",
    "url": "http://ample-zeno-10.radiojar.com/w4v1hckvewwtv?rj-ttl=5&rj-token=AAABZjcDL3GcLe-oq7bxP93xUwuPc3wHfEc68bGEdvD-4s2pJdkDlQ",
    "favicon": "http://www.medinabayekaffrine.net/wp-content/uploads/2017/04/logosite10-Récupéré00.png",
    "tags": "",
    "countrycode": "SN",
    "state": "",
    "language": "",
    "votes": 101,
    "codec": "MP3",
    "bitrate": 0,
    "hls": 0
  },
  {
    "stationuuid": "964258d0-0601-11e8-ae97-52543be04c81",
    "name": "Nostalgie 90.3 Dakar",
    "url": "http://206.190.135.28:8326/;stream.mp3",
    "favicon": "https://cdn-radiotime-logos.tunein.com/s6974q.png",
    "tags": "pop",
    "countrycode": "SN",
    "state": "",
    "language": "french",
    "votes": 93,
    "codec": "MP3",
    "bitrate": 128,
    "hls": 0
  },
  {
    "stationuuid": "962f7b81-0601-11e8-ae97-52543be04c81",
    "name": "Radio AlloDakar - TamTam Online",
    "url": "http://68.168.101.146:8520/;",
    "favicon": "http://allodakar.com/wp-content/uploads/2015/08/images2.jpg",
    "tags": "african music",
    "countrycode": "SN",
    "state": "Dakar",
    "language": "french",
    "votes": 71,
    "codec": "MP3",
    "bitrate": 64,
    "hls": 0
  },
  {
    "stationuuid": "2c355036-c696-11e8-a498-52543be04c81",
    "name": "Faydatidianiya",
    "url": "http://listen.senemultimedia.net:5526/listen/1/",
    "favicon": "https://www.faydatidianiya.com/fr///templates/ts_news247/images/favicon.ico",
    "tags": "",
    "countrycode": "SN",
    "state": "",
    "language": "",
    "votes": 26,
    "codec": "MP3",
    "bitrate": 128,
    "hls": 0
  }
]