[
  {
    "stationuuid": "9616a843-0601-11e8-ae97-52543be04c81",
    "name": "Mosaique FM",
    "url": "http://radio.mosaiquefm.net:8000/mosalive",
    "favicon": "http://www.tunisie-radio.com/sites/default/files/radio/mosaique-fm_0.png",
    "tags": "",
    "countrycode": "TN",
    "state": "Tunis",
    "language": "arabic",
    "votes": 1291,
    "codec": "MP3",
    "bitrate": 90,
    "hls": 0
  },
  {
    "stationuuid": "961ee9aa-0601-11e8-ae97-52543be04c81",
    "name": "Jawhara FM",
    "url": "http://streaming2.toutech.net:8000/jawharafm",
    "favicon": "https://lh3.googleusercontent.com/5JDzffziO_SyP6qd6Tvpx_OJJJvQoFS0sUNyPibaZrI4YjdckmaW6MYWAHbs4O37OyA=w300",
    "tags": "",
    "countrycode": "TN",
    "state": "Sousse",
    "language": "arabic",
    "votes": 720,
    "codec": "MP3",
    "bitrate": 128,
    "hls": 0
  },
  {
    "stationuuid": "ccac6135-cd73-4786-8e69-666df05a5881",
    "name": "Radio IFM",
    "url": "https://live.ifm.tn/radio/8000/ifmlive",
    "favicon": "https://www.ifm.tn/images/logo.png",
    "tags": "news,entertainment,music",
    "countrycode": "TN",
    "state": "",
    "language": "arabic",
    "votes": 8,
    "codec": "MP3",
    "bitrate": 128,
    "hls": 0
  },
  {
    "stationuuid": "96370554-0601-11e8-ae97-52543be04c81",
    "name": "Express FM",
    "url": "http://expressfm.ice.infomaniak.ch/expressfm-64.mp3",
    "favicon": "https://radioexpressfm.com/wp-content/uploads/2021/05/cropped-EXPRESS_LOGO-CMJN_FINAL.png",
    "tags": "",
    "countrycode": "TN",
    "state": "Tunis",
    "language": "arabic",
    "votes": 192,
    "codec": "MP3",
    "bitrate": 128,
    "hls": 0
  },
  {
    "stationuuid": "96357cd1-0601-11e8-ae97-52543be04c81",
    "name": "Nejma FM",
    "url": "http://188.166.109.186:8000/stream",
    "favicon": "https://yt3.ggpht.com/-x17-zbWskOw/AAAAAAAAAAI/AAAAAAAAAAA/kDkULqu-s8c/s900-c-k-no-mo-rj-c0xffffff/photo.jpg",
    "tags": "",
    "countrycode": "TN",
    "state": "Sousse",
    "language": "arabic",
    "votes": 169,
    "codec": "MP3",
    "bitrate": 128,
    "hls": 0
  },
  {
    "stationuuid": "964863b9-0601-11e8-ae97-52543be04c81",
    "name": "RTCI",
    "url": "http://rtstream.tanitweb.com/rtci",
    "favicon": "http://www.rtci.tn/wp-content/themes/mycms.1.0.0/library/images/main-logo.png",
    "tags": "",
    "countrycode": "TN",
    "state": "Tunis",
    "language": "multilingual",
    "votes": 130,
    "codec": "MP3",
    "bitrate": 128,
    "hls": 0
  },
  {
    "stationuuid": "96376cb7-0601-11e8-ae97-52543be04c81",
    "name": "Radio Med",
    "url": "http://stream6.tanitweb.com/radiomed",
    "favicon": "http://db.radioline.fr/pictures/radio_80ccc7f0a13d06b6df03bc1d6bfe8dc1/logo200.jpg?size=200",
    "tags": "",
    "countrycode": "TN",
    "state": "Nabeul",
    "language": "arabic",
    "votes": 196,
    "codec": "MP3",
    "bitrate": 128,
    "hls": 0
  },
  {
    "stationuuid": "eebcbc0c-b326-11e8-afe1-52543be04c81",
    "name": "Radio Sfax",
    "url": "http://rtstream.tanitweb.com/sfax",
    "favicon": "http://www.radiosfax.tn/wp-content/themes/mycms.1.0.0/favicon.png",
    "tags": "",
    "countrycode": "TN",
    "state": "صفاقس",
    "language": "arabic",
    "votes": 127,
    "codec": "MP3",
    "bitrate": 128,
    "hls": 0
  },
  {
    "stationuuid": "9d700788-501d-44c0-86c4-bab8e45881fa",
    "name": "Radio Nationale",
    "url": "http://rtstream.tanitweb.com/nationale",
    "favicon": "https://mytuner.global.ssl.fastly.net/media/tvos_radios/HM6AJPJ422.png",
    "tags": "classical",
    "countrycode": "TN",
    "state": "",
    "language": "",
    "votes": 14,
    "codec": "MP3",
    "bitrate": 128,
    "hls": 0
  },
  {
    "stationuuid": "df3d656e-70d7-11e8-83fa-52543be04c81",
    "name": "Radio Quran Karim",
    "url": "http://5.135.194.225:8000/live.m3u",
    "favicon": "http://www.tunisie-radio.com/sites/default/files/radio/radio-quran-dh-lqran.jpg",
    "tags": "",
    "countrycode": "TN",
    "state": "",
    "language": "arabic",
    "votes": 269,
    "codec": "MP3",
    "bitrate": 24,
    "hls": 0
  },
  {
    "stationuuid": "96376b69-0601-11e8-ae97-52543be04c81",
    "name": "Sabra FM",
    "url": "http://stream6.tanitweb.com/sabrafm",
    "favicon": "https://mytuner.global.ssl.fastly.net/media/tvos_radios/kez39uhhpmwe.jpg",
    "tags": "Talk,Variety,Arabic music",
    "countrycode": "TN",
    "state": "Tunis",
    "language": "arabic",
    "votes": 184,
    "codec": "MP3",
    "bitrate": 128,
    "hls": 0
  },
  {
    "stationuuid": "861210ec-4470-11ea-a860-52543be04c81",
    "name": "Radio Chaker",
    "url": "http://radiochaker.th3experte.com/",
    "favicon": "https://i.ibb.co/DbkyBLw/61528442-2188641351189547-1471733611274174464-n.jpg",
    "tags": "th3experte.com,chaker hamzaoui,chaker,quran,القرآن الكريم",
    "countrycode": "TN",
    "state": "Kairouan",
    "language": "arabic",
    "votes": 168,
    "codec": "MP3",
    "bitrate": 128,
    "hls": 0
  },
  {
    "stationuuid": "963806f4-0601-11e8-ae97-52543be04c81",
    "name": "Radio Le Kef",
    "url": "http://rtstream.tanitweb.com/kef",
    "favicon": "https://upload.wikimedia.org/wikipedia/fr/thumb/5/59/Radio_Le_Kef.png/180px-Radio_Le_Kef.png",
    "tags": "",
    "countrycode": "TN",
    "state": "Kef",
    "language": "arabic",
    "votes": 158,
    "codec": "MP3",
    "bitrate": 128,
    "hls": 0
  },
  {
    "stationuuid": "9630c3be-0601-11e8-ae97-52543be04c81",
    "name": "Misk FM",
    "url": "http://178.32.253.134:8000/stream?type=.mp3",
    "favicon": "http://is4.mzstatic.com/image/thumb/Purple122/v4/f2/d9/02/f2d90216-ee8d-bf03-81ae-e67dd4f9c4ab/source/1200x630bb.jpg",
    "tags": "",
    "countrycode": "TN",
    "state": "Tunis",
    "language": "arabic",
    "votes": 156,
    "codec": "MP3",
    "bitrate": 192,
    "hls": 0
  },
  {
    "stationuuid": "5aeb698d-4c9b-11e8-a4d1-52543be04c81",
    "name": "Radio Monastir",
    "url": "http://rtstream.tanitweb.com/monastir",
    "favicon": "http://www.radiomonastir.tn/wp-content/themes/mycms.1.0.0/favicon.png",
    "tags": "mestir,monastir",
    "countrycode": "TN",
    "state": "Monastir",
    "language": "arabic",
    "votes": 154,
    "codec": "MP3",
    "bitrate": 128,
    "hls": 0
  },
  {
    "stationuuid": "56036d6b-b320-11e8-afe1-52543be04c81",
    "name": "Radio Jeunes",
    "url": "http://rtstream.tanitweb.com/jeunes",
    "favicon": "http://www.radiojeunes.tn/wp-content/themes/mycms.1.0.0/favicon.png",
    "tags": "",
    "countrycode": "TN",
    "state": "Tunis تونس",
    "language": "arabic",
    "votes": 141,
    "codec": "MP3",
    "bitrate": 128,
    "hls": 0
  },
  {
    "stationuuid": "350aab0e-70cc-11e8-83fa-52543be04c81",
    "name": "إذاعة القرآن الكريم",
    "url": "http://5.135.194.225:8000/live.m3u",
    "favicon": "http://5.135.194.225:8000/favicon.ico",
    "tags": "",
    "countrycode": "TN",
    "state": "",
    "language": "arabic",
    "votes": 141,
    "codec": "MP3",
    "bitrate": 24,
    "hls": 0
  },
  {
    "stationuuid": "9630755d-0601-11e8-ae97-52543be04c81",
    "name": "Karama FM",
    "url": "http://serveur.wanastream.com:64900/;",
    "favicon": "https://mytuner.global.ssl.fastly.net/media/tvos_radios/eunv787zhsvu.png",
    "tags": "",
    "countrycode": "TN",
    "state": "Sidi Bouzid",
    "language": "arabic",
    "votes": 133,
    "codec": "MP3",
    "bitrate": 160,
    "hls": 0
  },
  {
    "stationuuid": "fc40425a-b324-11e8-afe1-52543be04c81",
    "name": "Radio Tataouine",
    "url": "http://rtstream.tanitweb.com/tataouine",
    "favicon": "http://www.radiotataouine.tn/wp-content/themes/mycms.1.0.0/favicon.png",
    "tags": "",
    "countrycode": "TN",
    "state": "Tataouine تطاوين",
    "language": "arabic",
    "votes": 132,
    "codec": "MP3",
    "bitrate": 128,
    "hls": 0
  },
  {
    "stationuuid": "dd53a994-9142-11e8-a767-52543be04c81",
    "name": "jawhara",
    "url": "http://streaming2.toutech.net:8000/jawharafm",
    "favicon": "",
    "tags": "",
    "countrycode": "TN",
    "state": "",
    "language": "arabic,frensh",
    "votes": 75,
    "codec": "MP3",
    "bitrate": 128,
    "hls": 0
  },
  {
    "stationuuid": "9645b15d-0601-11e8-ae97-52543be04c81",
    "name": "Radio Lamma",
    "url": "http://listen.radionomy.com/lamma-radio1",
    "favicon": "https://scontent.ftun3-1.fna.fbcdn.net/v/t1.0-9/21740229_1573181632721427_3511711754329711880_n.jpg?oh=14bba052f013bfe7564a86c7de443427&oe=5A781F76",
    "tags": "",
    "countrycode": "TN",
    "state": "Sfax",
    "language": "arabic",
    "votes": 66,
    "codec": "MP3",
    "bitrate": 128,
    "hls": 0
  },
  {
    "stationuuid": "86518279-6af6-11ea-b1cf-52543be04c81",
    "name": "Radio Nefzawa",
    "url": "http://51.83.76.244:8020/radio.mp3",
    "favicon": "https://i0.wp.com/radionefzawa.net/wp-content/uploads/2018/09/cropped-LOGO-png.png?fit=512%2C512",
    "tags": "",
    "countrycode": "TN",
    "state": "",
    "language": "arabic",
    "votes": 11,
    "codec": "MP3",
    "bitrate": 128,
    "hls": 0
  },
  {
    "stationuuid": "1000001e-d8a2-11e9-a861-52543be04147",
    "name": "Mosaique FM Gold",
    "url": "https://radio.mosaiquefm.net/mosagold?1640942878783",
    "favicon": "https://www.tunisie-radio.com/sites/default/files/styles/medium_2/public/radio/mosaique-fm-gold.png?itok=-GF_tFoN",
    "tags": "Oldies",
    "countrycode": "TN",
    "state": "Tunis",
    "language": "arabic",
    "votes":  12,
    "codec": "MP3",
    "bitrate":  128,
    "hls":  0
  },
  {
    "stationuuid": "3c698a57-3599-47c8-bfd4-58be19fc31d1",
    "name": "Mosaique FM Tarab",
    "url": "http://radio.mosaiquefm.net:8000/mosatarab",
    "favicon": "",
    "tags": "classical",
    "countrycode": "TN",
    "state": "",
    "language": "",
    "votes": 6,
    "codec": "MP3",
    "bitrate": 128,
    "hls": 0
  },
  {
    "stationuuid": "b6ad4afe-7214-4f33-b012-dd1df6112165",
    "name": "Mosaique FM Tounsi",
    "url": "https://radio.mosaiquefm.net/mosatounsi",
    "favicon": "",
    "tags": "classical",
    "countrycode": "TN",
    "state": "",
    "language": "",
    "votes": 4,
    "codec": "MP3",
    "bitrate": 128,
    "hls": 0
  },
  {
    "stationuuid": "a9a5202a-dc7c-40a2-8104-9e38d2707882",
    "name": "Radio ML",
    "url": "http://stream.tun-radio.com/radio/8060/ml.mp3",
    "favicon": "",
    "tags": "classical",
    "countrycode": "TN",
    "state": "",
    "language": "",
    "votes": 1,
    "codec": "MP3",
    "bitrate": 64,
    "hls": 0
  },
  {
    "stationuuid": "471e2aef-b20c-4623-a89d-4577c293d0d9",
    "name": "Panorama Tunis",
    "url": "https://stream.tun-radio.com/radio/8000/panorama_92",
    "favicon": "",
    "tags": "international",
    "countrycode": "TN",
    "state": "",
    "language": "",
    "votes": 0,
    "codec": "MP3",
    "bitrate": 96,
    "hls": 0
  },
  {
    "stationuuid": "960b2a43-0601-11e8-ae97-52543be04c81",
    "name": "Shems FM",
    "url": "http://stream6.tanitweb.com/shems",
    "favicon": "http://tunisiefm.net/sites/default/files/radio/logos/logo-shems-fm.jpg",
    "tags": "top 40,pop",
    "countrycode": "TN",
    "language": "arabic",
    "votes": "678",
    "codec": "MP3",
    "bitrate": "128",
    "hls": 0
  },
  {
    "stationuuid": "96489ab5-0601-11e8-ae97-52543be04c81",
    "name": "BBC Arabic",
    "url": "http://bbcwssc.ic.llnwd.net/stream/bbcwssc_mp1_ws-araba_backup",
    "favicon": "https://storage.googleapis.com/alsjlstorage.appspot.com/300/69.jpg",
    "tags": "news,arabic programming,bbc",
    "countrycode": "GB",
    "language": "arabic",
    "votes": "457",
    "codec": "MP3",
    "bitrate": "56",
    "hls": 0
  },
  {
    "stationuuid": "96134297-0601-11e8-ae97-52543be04c81",
    "name": "Nogoum FM 100.6",
    "url": "http://ice31.securenetsystems.net/NOGOUM?&playSessionID=7B8C5642-DA25-C192-E7BF09B06CCA24E4",
    "favicon": "https://gp1.wac.edgecastcdn.net/802892/http_public_production/artists/images/3297554/original/hash:1467425443/resize:400x400/1366240977_57748814.png?1467425443",
    "countrycode": "EG",
    "state": "Cairo",
    "language": "arabic",
    "votes": "862",
    "codec": "AAC",
    "bitrate": "64",
    "hls": 0
  },
  {
    "stationuuid": "961cc33e-0601-11e8-ae97-52543be04c81",
    "name": "HitRadio",
    "url": "http://hitradio-maroc.ice.infomaniak.ch/hitradio-maroc-128.mp3",
    "favicon": "https://scontent.ftun3-1.fna.fbcdn.net/v/t1.0-9/10646677_10153364200929947_979182071976267060_n.png?oh=e07086bad4a6a72bb031cbb89d142941&oe=5A7F2F35",
    "tags": "contemporary hits,top 40",
    "countrycode": "MA",
    "state": "Rabat",
    "language": "arabic",
    "votes": "660",
    "codec": "MP3",
    "bitrate": "112",
    "hls": 0
  },
  {
    "stationuuid": "fef77ae6-6866-11e9-af37-52543be04c81",
    "name": "Jil FM",
    "url": "http://jil-fm.ice.infomaniak.ch/jilfm.aac",
    "favicon": "http://radioalgerie.dz/player/sites/default/files/logo_2.ico",
    "tags": "radio algerienne,jilfm",
    "countrycode": "DZ",
    "state": "Alger",
    "language": "arabic",
    "votes": "143",
    "codec": "AAC+",
    "bitrate": "64",
    "hls": 0
  },
  {
    "stationuuid": "9645a9e8-0601-11e8-ae97-52543be04c81",
    "name": "Alif Alif FM",
    "url": "http://www.alifaliffm.com:8800/AlifAlif.mp3?type=.mp3/;stream.mp3",
    "favicon": "https://encrypted-tbn0.gstatic.com/images?q=tbn:ANd9GcQg0HFOQtozENa52jp4uRq1f9LpcOVXmUEV4WVsj_As2_m4cJPz",
    "countrycode": "SA",
    "state": "Riyadh",
    "language": "arabic",
    "votes": "380",
    "codec": "MP3",
    "bitrate": "128",
    "hls": 0
  },
  {
    "stationuuid": "9645369b-0601-11e8-ae97-52543be04c81",
    "name": "Medi 1",
    "url": "http://live.medi1.com/medi1?.mp3",
    "favicon": "https://www.medi1.com/favicon.ico",
    "countrycode": "MA",
    "state": "Tanger",
    "language": "arabic",
    "votes": "714",
    "codec": "MP3",
    "bitrate": "128",
    "hls": 0
  },
  {
    "stationuuid": "96449278-0601-11e8-ae97-52543be04c81",
    "name": "Saudi Quran",
    "url": "http://quraan.us:9944/;stream.mp3",
    "favicon": "http://quran.sr.sa/http%3A%2F%2Falquranalkareem.saudiaradio.net%2Fimg%2Ffb_ogtags%2Ffbogimg.png",
    "countrycode": "SA",
    "state": "Riyadh",
    "language": "arabic",
    "votes": "378",
    "codec": "MP3",
    "bitrate": "128",
    "hls": 0
  },
  {
    "stationuuid": "c4354512-1a51-11e8-a334-52543be04c81",
    "name": "ASWAT",
    "url": "http://broadcast.ice.infomaniak.ch/aswat-high.mp3",
    "favicon": "http://www.radioaswat.ma//style/img/favicon.ico",
    "countrycode": "MA",
    "language": "arabic",
    "votes": "297",
    "codec": "MP3",
    "bitrate": "96",
    "hls": 0
  },
  {
    "stationuuid": "964535e3-0601-11e8-ae97-52543be04c81",
    "name": "MedRadio",
    "url": "http://medradio-maroc.ice.infomaniak.ch/medradio-maroc-64.mp3?.mp3",
    "favicon": "http://www.medradio.ma/wp-content/uploads/2017/03/cropped-logo-mof-270x270.png",
    "countrycode": "MA",
    "language": "arabic",
    "votes": "966",
    "codec": "MP3",
    "bitrate": "96",
    "hls": 0
  },
  {
    "stationuuid": "96489ecc-0601-11e8-ae97-52543be04c81",
    "name": "Mix FM",
    "url": "http://s2.voscast.com:11376/;",
    "favicon": "https://static.wixstatic.com/media/f47a3e_daf5380428b94d4192f8eaf2f0c59e62~mv2.jpg/v1/fill/w_221,h_221,al_c,lg_1,q_80/f47a3e_daf5380428b94d4192f8eaf2f0c59e62~mv2.webp",
    "countrycode": "SA",
    "state": "Riyadh",
    "language": "arabic",
    "votes": "263",
    "codec": "MP3",
    "bitrate": "96",
    "hls": 0
  },
  {
    "stationuuid": "96321b70-0601-11e8-ae97-52543be04c81",
    "name": "Arabic 90s FM",
    "url": "http://64.150.176.192:8276/",
    "countrycode": "EG",
    "state": "Cairo",
    "language": "arabic",
    "votes": "320",
    "codec": "MP3",
    "bitrate": "64",
    "hls": 0
  },
  {
    "stationuuid": "9644efa9-0601-11e8-ae97-52543be04c81",
    "name": "إذاعة السنة",
    "url": "http://andromeda.shoutca.st:8189/live",
    "favicon": "http://static.radio.net/images/broadcasts/ec/8b/104358/1/c175.png",
    "countrycode": "SA",
    "state": "Riyadh",
    "language": "arabic",
    "votes": "301",
    "codec": "MP3",
    "bitrate": "32",
    "hls": 0
  },
  {
    "stationuuid": "9645ad42-0601-11e8-ae97-52543be04c81",
    "name": "Rotana FM",
    "url": "http://curiosity.shoutca.st:6035/;",
    "favicon": "https://mytuner.global.ssl.fastly.net/media/tvos_radios/xemw8sax5tqq.jpg",
    "countrycode": "SA",
    "state": "Riyadh",
    "language": "arabic",
    "votes": "270",
    "codec": "MP3",
    "bitrate": "48",
    "hls": 0
  },
  {
    "stationuuid": "96104f13-0601-11e8-ae97-52543be04c81",
    "name": "Radio Masr 88.7",
    "url": "http://streaming.radio.co/scc13a6b96/listen",
    "favicon": "https://lh4.ggpht.com/1wkXSH2IUHQfvtsXh0boaH8w-WaJlAH7sUiS9mPOJl6kCs21AbrfjqaZkXqXKVqx1A=w300",
    "countrycode": "EG",
    "state": "Cairo",
    "language": "arabic",
    "votes": "464",
    "codec": "AAC",
    "bitrate": "128",
    "hls": 0
  },
  {
    "stationuuid": "6904f08e-54b6-11e8-b0ce-52543be04c81",
    "name": "Raidzair",
    "url": "https://www.rcast.net/tunein.php?stream=http://188.165.242.25:8020/stream/&type=m3u",
    "favicon": "https://www.rcast.net///favicon.png",
    "tags": "rai",
    "countrycode": "DZ",
    "language": "arabic",
    "votes": "205",
    "codec": "MP3",
    "bitrate": "128",
    "hls": 0
  },
  {
    "stationuuid": "961a5858-0601-11e8-ae97-52543be04c81",
    "name": "Radio 9090 90.9",
    "url": "http://9090streaming.mobtada.com/9090FMEGYPT",
    "favicon": "http://onaeg.com/wp-content/uploads/2016/10/28bxybl.png",
    "countrycode": "EG",
    "state": "Cairo",
    "language": "arabic",
    "votes": "423",
    "codec": "MP3",
    "bitrate": "192",
    "hls": 0
  },
  {
    "stationuuid": "0d52ce5c-d019-11e9-a861-52543be04c81",
    "name": "lbi Zaman",
    "url": "http://212.83.138.48:8165/stream",
    "favicon": "http://lbiradio.com/zaman/lbi-zaman.jpg",
    "tags": "arabic classic,arabic music,arabic oldies,classic arabic,tarab",
    "countrycode": "EG",
    "state": "Cairo",
    "language": "arabic",
    "votes": "158",
    "codec": "MP3",
    "bitrate": "128",
    "hls": 0
  },
  {
    "stationuuid": "96498332-0601-11e8-ae97-52543be04c81",
    "name": "Radio Sawa Egypt",
    "url": "https://mbn-channel-03.akacast.akamaistream.net/7/31/233452/v1/ibb.akacast.akamaistream.net/mbn_channel_03?download=1",
    "favicon": "https://www.radiosawa.com//Content/responsive/MBN/ar-SAW/img/webApp/ico-144x144.png",
    "countrycode": "EG",
    "language": "arabic",
    "votes": "382",
    "codec": "MP3",
    "bitrate": "0",
    "hls": 0
  },
  {
    "stationuuid": "4dc583f7-c3b3-11e8-aaf2-52543be04c81",
    "name": "El Radio 9090 FM",
    "url": "http://9090streaming.mobtada.com/9090FMEGYPT",
    "favicon": "https://mytuner.global.ssl.fastly.net/media/tvos_radios/ddvJvW8kCA.png",
    "tags": "local music,music",
    "countrycode": "EG",
    "language": "arabic",
    "votes": "232",
    "codec": "MP3",
    "bitrate": "192",
    "hls": 0
  },
  {
    "stationuuid": "9653bbbe-c3a2-11e8-aaf2-52543be04c81",
    "name": "Radio 90s FM - راديو أف أم التسعينات",
    "url": "http://64.150.176.192:8276/;",
    "favicon": "https://www.liveonlineradio.net/wp-content/uploads/2014/06/radio-nineties-fm.jpg",
    "tags": "local music,world music,music",
    "countrycode": "EG",
    "language": "arabic",
    "votes": "273",
    "codec": "MP3",
    "bitrate": "64",
    "hls": 0
  },
  {
    "stationuuid": "c1d8bcf1-c763-11e8-a54a-52543be04c81",
    "name": "Radio FM 95 راديو شعبي",
    "url": "http://178.32.62.154:9010/",
    "favicon": "https://4.bp.blogspot.com/-aTiedlwgPwE/WuCvlPt818I/AAAAAAAAFQM/qEWCoVazhrghX3JIBoVEwdvgpYLxGICOACLcBGAs/s1600/radio-95-fm-pop-live.jpg",
    "tags": "local music,music",
    "countrycode": "EG",
    "language": "arabic",
    "votes": "331",
    "codec": "MP3",
    "bitrate": "128",
    "hls": 0
  },
  {
    "stationuuid": "96411440-0601-11e8-ae97-52543be04c81",
    "name": "Medina FM",
    "url": "http://medinafm.ice.infomaniak.ch/medinafm-64.mp3?.mp3",
    "favicon": "http://www.allzicradio.com/media/radios/medina-fm.jpg",
    "countrycode": "MA",
    "state": "Meknès",
    "language": "arabic",
    "votes": "249",
    "codec": "MP3",
    "bitrate": "64",
    "hls": 0
  },
  {
    "stationuuid": "9645afb9-0601-11e8-ae97-52543be04c81",
    "name": "Banha City FM",
    "url": "http://listen.radionomy.com/banhacity?type=.mp3/;stream.mp3",
    "favicon": "https://mytuner.global.ssl.fastly.net/media/tvos_radios/fLjJSVRhu6.jpg",
    "countrycode": "EG",
    "state": "Cairo",
    "language": "arabic",
    "votes": "281",
    "codec": "MP3",
    "bitrate": "128",
    "hls": 0
  }
]